round_to_n_significant_digits/__init__.py
round_to_n_significant_digits/main.py
round_to_n_significant_digits-0.1.5.dist-info/LICENSE.txt
round_to_n_significant_digits-0.1.5.dist-info/WHEEL
round_to_n_significant_digits-0.1.5.dist-info/METADATA
round_to_n_significant_digits-0.1.5.dist-info/RECORD
